{"garden_garden-rss_index.md":"fIpIwWmR","now_index.md":"CNyD7Dlz","index.md":"Nj_Hdy6a","guide-to-incrementals_index.md":"xmrRwqNj","guide-to-incrementals_ludology_appeal-developers_index.md":"BckVNqaa","guide-to-incrementals_ludology_definition_index.md":"CxjRYfXR","garden_v-ecs_index.md":"CZUAgrLk","garden_vitepress_index.md":"BENEgkWy","garden_wanderstop_index.md":"D8uPUKmB","garden_webrings_index.md":"DSLB6tRV","guide-to-incrementals_ludology_appeal-gamers_index.md":"aySUdrTu","guide-to-incrementals_ludology_content_index.md":"iU4CjqQ8","garden_command-palettes_index.md":"CERfDABF","garden_art-is-never-complete_index.md":"CzZxEsFP","garden_activitypub_index.md":"C7Pcc_jp","garden_artificial-intelligence_index.md":"Di9UXEyc","garden_consensus-democracy_index.md":"Ch4ZfYXj","garden_video-game-monetization_index.md":"d95UgkuV","garden_cinny_index.md":"mHBMIGDW","guide-to-incrementals_design_criticism_index.md":"B6ukqwEl","garden_decentralized_index.md":"BF1rWxy7","garden_weird_index.md":"DNu9Jbkq","public_gamedevtree_readme.md":"DE0tbltW","garden_game-dev-tree_index.md":"Bs6To0IE","garden_digital-gardens_index.md":"lirsauqL","garden_this-knowledge-hub_index.md":"uV7Eiijt","public_kronos_docs_trees-and-tree-customization.md":"CIBisQ1N","public_kronos_docs_basic-layer-breakdown.md":"B8H1fhgA","public_kronos_readme.md":"gWCvo8NR","public_kronos_docs_challenges.md":"Cs3Vfgw-","public_kronos_docs_custom-tab-layouts.md":"livval5T","garden_premium-currency_index.md":"DGPhF_iv","garden_prescriptivism-vs-descriptivism_index.md":"BDllpyQE","garden_representative-democracy_index.md":"DnhQ3BQZ","garden_social-media_index.md":"C5MDkd5V","garden_scientific-constructivism_index.md":"CCxms8OE","garden_social-constructs_index.md":"B89zb1vd","garden_synapse_index.md":"DoUu8nOC","garden_my-projects_index.md":"CyPrjLGe","garden_neoliberalism_index.md":"COCPteqK","garden_technocracy_index.md":"D9bRvioQ","garden_logseq_index.md":"BKx9nbvs","garden_my-political-beliefs_index.md":"DDOVqywZ","garden_matrix_index.md":"BKR0IM8u","garden_my-political-journey_index.md":"DBd-sw5A","garden_mbin_index.md":"CKBJmR1K","garden_babble-buds_index.md":"kcIqe3w3","garden_chat-glue_index.md":"CZybzMdR","garden_profectus_index.md":"rJ9jCI0G","garden_my-personal-website_index.md":"Bjexj3hm","garden_my-browser-stack_index.md":"DgAx9z3r","garden_guide-to-incrementals_appeal-to-players_index.md":"C1OWiPJh","garden_nostr_index.md":"jOWnyx9U","garden_mtx_index.md":"DLO-dm-y","garden_freeform-vs-chronological-dichotomy_index.md":"DD9ZuP_1","garden_network-of-knowledge_index.md":"zfippqNL","garden_incremental-social_index.md":"DUr7xeNn","changelog_index.md":"D4S7sVbP","garden_guide-to-incrementals_defining-the-genre_index.md":"DwNrtuwu","garden_guide-to-incrementals_index.md":"3kSQrG2d","garden_guide-to-incrementals_what-is-content_index.md":"Chrm3YrK","garden_guide-to-incrementals_navigating-criticism_index.md":"CiUY0uTl","garden_forgejo_index.md":"UDKB0uWO","garden_anarchism_index.md":"CWkdv0cI","garden_fedi-v2_index.md":"BHX7tNM1","garden_chronological_index.md":"h4HY5Bgm","garden_fediverse_index.md":"BoXrPQN_","garden_capture-the-citadel_index.md":"DHIWdke5","garden_chromatic-lattice_index.md":"0-rVV5gS","garden_the-small-web_index.md":"BXH8fhsd","garden_gerrymandering_index.md":"BhmEyVv-","garden_direct-democracy_index.md":"BNOVuxOq","garden_guide-to-incrementals_appeal-to-developers_index.md":"kmCs2_fk","garden_davey-wreden_index.md":"CD-CGjU3","garden_dice-armor_index.md":"tEzrtSbq","garden_kronos_index.md":"D2g1DvPc","garden_individualism_index.md":"Da4RJ02M","garden_ivy-road_index.md":"vZ4p0HqK","garden_local-communities_index.md":"BszpJGLX","garden_life-is-strange_index.md":"CeJhbrqn","garden_open-source_index.md":"CZ63RIUB","garden_atproto_index.md":"B-OmYkJd","garden_freeform_index.md":"BTtAw5DL","garden_gender_index.md":"HMsh5jKw","garden_federated-identity_index.md":"B6IBg3yU","garden_objectivity_index.md":"DuASP0T3","garden_gender-performativity_index.md":"DeCn-tNm","garden_opti-speech_index.md":"B5f5Bu0h","garden_local-first-software_index.md":"C98NALRg","public_lit_docs_achievements.md":"DxD0wCNF","garden_a-plea-to-organize_index.md":"CmNRyDtz","public_lit_docs_bars.md":"DclDejG3","public_gamedevtree_docs_infoboxes.md":"bLloeIuf","public_lit_docs_buyables.md":"78Vp9b6u","public_lit_docs_custom-tab-layouts.md":"BoQJFtTn","public_lit_docs_basic-layer-breakdown.md":"CsZKnxwf","public_lit_docs_getting-started.md":"CK27tjNE","public_lit_docs_challenges.md":"Z9Rj0YIU","public_lit_docs_clickables.md":"BH0xyi8n","public_lit_docs_infoboxes.md":"CuZo0M8o","public_lit_docs_main-mod-info.md":"BMD6V4Fr","public_lit_docs_milestones.md":"DW0yfQPK","public_lit_docs_upgrades.md":"B0k22Nxf","public_lit_docs_trees-and-tree-customization.md":"C9RmdUn6","public_lit_docs_updating-tmt.md":"KobKYOhn","public_lit_docs_subtabs-and-microtabs.md":"_yQ1-Rr1","public_gamedevtree_changelog.md":"33CNNJKT","garden_commune_index.md":"DRm7jW08","garden_the-beginner-s-guide_index.md":"Clcjdv6l","garden_the-indieweb_signature-blocks_index.md":"DoMxMghP","garden_personality_index.md":"DZsXec9F","garden_pre-order-bonuses_index.md":"COGcpSmA","garden_orchard_index.md":"Bh9zMUaM","public_gamedevtree_2.0-format-changes.md":"Bczdru-g","garden_the-cozy-web_index.md":"CxX8czNg","garden_political-quizzes_index.md":"Cj3ex64C","public_kronos_docs_particles.md":"DUOsroj0","public_kronos_docs_subtabs-and-microtabs.md":"CE1p7Oy-","public_kronos_docs_main-mod-info.md":"P75-j5rD","garden_planar-pioneers_index.md":"DT-Sgwbs","garden_the-indieweb_amplification_index.md":"DGCB_jZx","public_kronos_docs_milestones.md":"C15QtFf1","public_lit_docs_!general-info.md":"DJIpd8t5","public_kronos_docs_infoboxes.md":"DoJEZ-co","public_kronos_old things_2.0-format-changes.md":"QUX27CIC","public_kronos_docs_upgrades.md":"Di0rXgVe","public_lit_readme.md":"CsmWLhmX","public_gamedevtree_docs_clickables.md":"Ck1H6VJz","public_lit_old things_2.0-format-changes.md":"BZuK-caS","public_kronos_changelog.md":"D-HmMLD4","garden_trans-athletes-in-sports_index.md":"BX7S0MO3","public_kronos_docs_bars.md":"CSguFZp_","public_gamedevtree_docs_!general-info.md":"DE0Ke1e2","public_kronos_docs_achievements.md":"KsbXJC1r","public_kronos_docs_!general-info.md":"DBOKRLme","public_gamedevtree_docs_upgrades.md":"PvuguZyE","public_gamedevtree_docs_bars.md":"CUbXgosN","public_gamedevtree_docs_achievements.md":"C0yB95Wu","public_kronos_docs_buyables.md":"Bnk8zkua","public_kronos_docs_clickables.md":"BjE13u2w","public_kronos_docs_layer-features.md":"B0ijhoip","public_gamedevtree_docs_main-mod-info.md":"BCNaY-_6","public_kronos_docs_getting-started.md":"mxo4iirj","public_gamedevtree_docs_custom-tab-layouts.md":"DNTfGub2","public_gamedevtree_docs_getting-started.md":"hNeDDqaD","public_gamedevtree_docs_buyables.md":"B23LDgI6","public_lit_changelog.md":"CthDV5ot","public_kronos_docs_updating-tmt.md":"M9T22mdH","public_gamedevtree_docs_basic-layer-breakdown.md":"Yqwj_xfc","public_gamedevtree_docs_updating-tmt.md":"BX_YXvdE","public_kronos_docs_grids.md":"D6W3aZvd","about_index.md":"YpmaDm_z","garden_advent-incremental_index.md":"P8r1CEJu","public_gamedevtree_docs_challenges.md":"CE_eHHwf","public_gamedevtree_docs_subtabs-and-microtabs.md":"CMFhzxtB","public_gamedevtree_docs_layer-features.md":"Crq83lMF","public_gamedevtree_docs_milestones.md":"CWaYObZs","garden_police-abolition_index.md":"D06XOoQK","public_lit_docs_layer-features.md":"4M5Xu4L1"}
